gmail_sender.py
gmail_cli-0.1.0.dist-info/METADATA
gmail_cli-0.1.0.dist-info/WHEEL
gmail_cli-0.1.0.dist-info/entry_points.txt
gmail_cli-0.1.0.dist-info/top_level.txt
gmail_cli-0.1.0.dist-info/RECORD
