Metadata-Version: 2.4
Name: gmail-cli
Version: 0.1.0
Summary: Gmail CLI sender tool using OAuth2 authentication for sending emails via Gmail API
Author-email: Stephan Fitzpatrick <knowsuchagency@gmail.com>
License-Expression: MIT
Project-URL: Homepage, https://github.com/knowsuchagency/gmail-cli
Project-URL: Repository, https://github.com/knowsuchagency/gmail-cli
Keywords: gmail,email,cli,oauth2,google-api
Classifier: Development Status :: 3 - Alpha
Classifier: Intended Audience :: Developers
Classifier: Intended Audience :: End Users/Desktop
Classifier: Programming Language :: Python :: 3
Classifier: Programming Language :: Python :: 3.8
Classifier: Programming Language :: Python :: 3.9
Classifier: Programming Language :: Python :: 3.10
Classifier: Programming Language :: Python :: 3.11
Classifier: Programming Language :: Python :: 3.12
Classifier: Topic :: Communications :: Email
Classifier: Topic :: Utilities
Requires-Python: >=3.8
Requires-Dist: google-api-python-client
Requires-Dist: google-auth
Requires-Dist: google-auth-oauthlib
Requires-Dist: google-auth-httplib2
Requires-Dist: click
Requires-Dist: markdown
Requires-Dist: Pygments
